{
  "efp_nh": {
    "DJF": {
      "efp": 0.2807,
      "months": [
        12,
        1,
        2
      ]
    },
    "JFM": {
      "efp": 0.2817,
      "months": [
        1,
        2,
        3
      ]
    },
    "FMA": {
      "efp": 0.2136,
      "months": [
        2,
        3,
        4
      ]
    },
    "MAM": {
      "efp": 0.1612,
      "months": [
        3,
        4,
        5
      ]
    },
    "AMJ": {
      "efp": 0.1775,
      "months": [
        4,
        5,
        6
      ]
    },
    "MJJ": {
      "efp": 0.1275,
      "months": [
        5,
        6,
        7
      ]
    },
    "JJA": {
      "efp": 0.1396,
      "months": [
        6,
        7,
        8
      ]
    },
    "JAS": {
      "efp": 0.1288,
      "months": [
        7,
        8,
        9
      ]
    },
    "ASO": {
      "efp": 0.0826,
      "months": [
        8,
        9,
        10
      ]
    },
    "SON": {
      "efp": 0.1,
      "months": [
        9,
        10,
        11
      ]
    },
    "OND": {
      "efp": 0.1379,
      "months": [
        10,
        11,
        12
      ]
    },
    "NDJ": {
      "efp": 0.1606,
      "months": [
        11,
        12,
        1
      ]
    }
  },
  "efp_nh_123": {
    "DJF": {
      "efp": 0.1544,
      "months": [
        12,
        1,
        2
      ]
    },
    "JFM": {
      "efp": 0.1497,
      "months": [
        1,
        2,
        3
      ]
    },
    "FMA": {
      "efp": 0.0991,
      "months": [
        2,
        3,
        4
      ]
    },
    "MAM": {
      "efp": 0.0663,
      "months": [
        3,
        4,
        5
      ]
    },
    "AMJ": {
      "efp": 0.0875,
      "months": [
        4,
        5,
        6
      ]
    },
    "MJJ": {
      "efp": 0.0525,
      "months": [
        5,
        6,
        7
      ]
    },
    "JJA": {
      "efp": 0.0765,
      "months": [
        6,
        7,
        8
      ]
    },
    "JAS": {
      "efp": 0.0381,
      "months": [
        7,
        8,
        9
      ]
    },
    "ASO": {
      "efp": 0.0421,
      "months": [
        8,
        9,
        10
      ]
    },
    "SON": {
      "efp": 0.0456,
      "months": [
        9,
        10,
        11
      ]
    },
    "OND": {
      "efp": 0.0588,
      "months": [
        10,
        11,
        12
      ]
    },
    "NDJ": {
      "efp": 0.0517,
      "months": [
        11,
        12,
        1
      ]
    }
  },
  "efp_nh_gt3": {
    "DJF": {
      "efp": 0.1616,
      "months": [
        12,
        1,
        2
      ]
    },
    "JFM": {
      "efp": 0.1544,
      "months": [
        1,
        2,
        3
      ]
    },
    "FMA": {
      "efp": 0.1189,
      "months": [
        2,
        3,
        4
      ]
    },
    "MAM": {
      "efp": 0.1027,
      "months": [
        3,
        4,
        5
      ]
    },
    "AMJ": {
      "efp": 0.0833,
      "months": [
        4,
        5,
        6
      ]
    },
    "MJJ": {
      "efp": 0.0825,
      "months": [
        5,
        6,
        7
      ]
    },
    "JJA": {
      "efp": 0.1139,
      "months": [
        6,
        7,
        8
      ]
    },
    "JAS": {
      "efp": 0.0961,
      "months": [
        7,
        8,
        9
      ]
    },
    "ASO": {
      "efp": 0.0741,
      "months": [
        8,
        9,
        10
      ]
    },
    "SON": {
      "efp": 0.0674,
      "months": [
        9,
        10,
        11
      ]
    },
    "OND": {
      "efp": 0.0891,
      "months": [
        10,
        11,
        12
      ]
    },
    "NDJ": {
      "efp": 0.1203,
      "months": [
        11,
        12,
        1
      ]
    }
  },
  "efp_sh": {
    "DJF": {
      "efp": 0.1434,
      "months": [
        12,
        1,
        2
      ]
    },
    "JFM": {
      "efp": 0.1461,
      "months": [
        1,
        2,
        3
      ]
    },
    "FMA": {
      "efp": 0.0971,
      "months": [
        2,
        3,
        4
      ]
    },
    "MAM": {
      "efp": 0.0762,
      "months": [
        3,
        4,
        5
      ]
    },
    "AMJ": {
      "efp": 0.0913,
      "months": [
        4,
        5,
        6
      ]
    },
    "MJJ": {
      "efp": 0.1552,
      "months": [
        5,
        6,
        7
      ]
    },
    "JJA": {
      "efp": 0.1767,
      "months": [
        6,
        7,
        8
      ]
    },
    "JAS": {
      "efp": 0.1158,
      "months": [
        7,
        8,
        9
      ]
    },
    "ASO": {
      "efp": 0.1109,
      "months": [
        8,
        9,
        10
      ]
    },
    "SON": {
      "efp": 0.1282,
      "months": [
        9,
        10,
        11
      ]
    },
    "OND": {
      "efp": 0.1426,
      "months": [
        10,
        11,
        12
      ]
    },
    "NDJ": {
      "efp": 0.1062,
      "months": [
        11,
        12,
        1
      ]
    }
  },
  "efp_sh_123": {
    "DJF": {
      "efp": 0.0975,
      "months": [
        12,
        1,
        2
      ]
    },
    "JFM": {
      "efp": 0.0817,
      "months": [
        1,
        2,
        3
      ]
    },
    "FMA": {
      "efp": 0.0589,
      "months": [
        2,
        3,
        4
      ]
    },
    "MAM": {
      "efp": 0.0298,
      "months": [
        3,
        4,
        5
      ]
    },
    "AMJ": {
      "efp": 0.0223,
      "months": [
        4,
        5,
        6
      ]
    },
    "MJJ": {
      "efp": 0.0379,
      "months": [
        5,
        6,
        7
      ]
    },
    "JJA": {
      "efp": 0.0432,
      "months": [
        6,
        7,
        8
      ]
    },
    "JAS": {
      "efp": 0.0497,
      "months": [
        7,
        8,
        9
      ]
    },
    "ASO": {
      "efp": 0.0199,
      "months": [
        8,
        9,
        10
      ]
    },
    "SON": {
      "efp": 0.0261,
      "months": [
        9,
        10,
        11
      ]
    },
    "OND": {
      "efp": 0.0477,
      "months": [
        10,
        11,
        12
      ]
    },
    "NDJ": {
      "efp": 0.0586,
      "months": [
        11,
        12,
        1
      ]
    }
  },
  "efp_sh_gt3": {
    "DJF": {
      "efp": 0.1013,
      "months": [
        12,
        1,
        2
      ]
    },
    "JFM": {
      "efp": 0.0963,
      "months": [
        1,
        2,
        3
      ]
    },
    "FMA": {
      "efp": 0.0883,
      "months": [
        2,
        3,
        4
      ]
    },
    "MAM": {
      "efp": 0.0919,
      "months": [
        3,
        4,
        5
      ]
    },
    "AMJ": {
      "efp": 0.0761,
      "months": [
        4,
        5,
        6
      ]
    },
    "MJJ": {
      "efp": 0.1316,
      "months": [
        5,
        6,
        7
      ]
    },
    "JJA": {
      "efp": 0.1582,
      "months": [
        6,
        7,
        8
      ]
    },
    "JAS": {
      "efp": 0.1316,
      "months": [
        7,
        8,
        9
      ]
    },
    "ASO": {
      "efp": 0.0856,
      "months": [
        8,
        9,
        10
      ]
    },
    "SON": {
      "efp": 0.0829,
      "months": [
        9,
        10,
        11
      ]
    },
    "OND": {
      "efp": 0.1129,
      "months": [
        10,
        11,
        12
      ]
    },
    "NDJ": {
      "efp": 0.0936,
      "months": [
        11,
        12,
        1
      ]
    }
  }
}